muffin_jinja2/__init__.py
muffin_jinja2/py.typed
muffin_jinja2-1.8.1.dist-info/LICENSE
muffin_jinja2-1.8.1.dist-info/METADATA
muffin_jinja2-1.8.1.dist-info/WHEEL
muffin_jinja2-1.8.1.dist-info/RECORD
