Metadata-Version: 2.1
Name: muffin-jinja2
Version: 1.8.1
Summary: Support Jinja2 templates for Muffin Framework
Home-page: https://github.com/klen/muffin-jinja2
License: MIT
Keywords: asyncio,trio,asgi,web,muffin,jinja,jinja2
Author: Kirill Klenov
Author-email: horneds@gmail.com
Requires-Python: >=3.9,<4.0
Classifier: Development Status :: 5 - Production/Stable
Classifier: Framework :: AsyncIO
Classifier: Framework :: Trio
Classifier: Intended Audience :: Developers
Classifier: License :: OSI Approved :: MIT License
Classifier: Programming Language :: Python
Classifier: Programming Language :: Python :: 3
Classifier: Programming Language :: Python :: 3.9
Classifier: Programming Language :: Python :: 3.10
Classifier: Programming Language :: Python :: 3.11
Classifier: Programming Language :: Python :: 3.12
Classifier: Topic :: Internet :: WWW/HTTP
Requires-Dist: jinja2
Requires-Dist: muffin
Project-URL: Repository, https://github.com/klen/muffin-jinja2
